hmni/__init__.py
hmni/input_helpers.py
hmni/matcher.py
hmni/preprocess.py
hmni/siamese_network.py
hmni/syllable_tokenizer.py
hmni/models/latin.tar.gz
hmni-0.1.8.dist-info/LICENSE
hmni-0.1.8.dist-info/METADATA
hmni-0.1.8.dist-info/WHEEL
hmni-0.1.8.dist-info/top_level.txt
hmni-0.1.8.dist-info/RECORD
