Metadata-Version: 2.1
Name: hmni
Version: 0.1.8
Summary: Fuzzy Name Matching with Machine Learning
Home-page: https://github.com/Christopher-Thornton/hmni
Author: Christopher Thornton
Author-email: christopher_thornton@outlook.com
License: MIT
Download-URL: https://github.com/Christopher-Thornton/hmni/archive/v0.1.8.zip
Keywords: fuzzy-matching,natural-language-processing,nlp,machine-learning,data-science,python,artificial-intelligence,ai
Platform: UNKNOWN
Classifier: Development Status :: 4 - Beta
Classifier: License :: OSI Approved :: MIT License
Classifier: Programming Language :: Python :: 3
Classifier: Programming Language :: Python :: 3.5
Classifier: Programming Language :: Python :: 3.6
Classifier: Programming Language :: Python :: 3.7
Classifier: Programming Language :: Python :: 3.8
Requires-Dist: tensorflow
Requires-Dist: pandas (>=0.25)
Requires-Dist: numpy
Requires-Dist: unidecode
Requires-Dist: fuzzywuzzy
Requires-Dist: abydos (==0.5.0)
Requires-Dist: scikit-learn
Requires-Dist: joblib
